[
  {
    "id": "1d153a17-320f-47fc-a300-c04574c96ee3",
    "name": "Said A",
    "is_deleted": false
  },
  {
    "id": "65e2b369-96a6-454a-a2f4-6513c20c1506",
    "name": "Ҳенри Марш",
    "is_deleted": false
  },
  {
    "id": "001",
    "name": "Uolter Ayzekson",
    "is_deleted": false
  },
  {
    "id": "002",
    "name": "Javlon Jovliyev",
    "is_deleted": false
  },
  {
    "id": "003",
    "name": "Abdulla Qodiriy",
    "is_deleted": false
  },
  {
    "id": "004",
    "name": "Xudoyberdi To'xtaboyev",
    "is_deleted": false
  },
  {
    "id": "005",
    "name": "Anvar Narzullayev",
    "is_deleted": false
  },
  {
    "id": "006",
    "name": "G'afur G'ulom",
    "is_deleted": false
  }
]